README.txt
cloudkey.py
setup.py
cloudkey.egg-info/PKG-INFO
cloudkey.egg-info/SOURCES.txt
cloudkey.egg-info/dependency_links.txt
cloudkey.egg-info/not-zip-safe
cloudkey.egg-info/requires.txt
cloudkey.egg-info/top_level.txt