Metadata-Version: 1.0
Name: cloudkey
Version: 1.2.6
Summary: Dailymotion Cloud API client library
Home-page: http://github.com/dailymotion/cloudkey-py
Author: Sebastien Estienne
Author-email: sebastien.estienne@gmail.com
License: Apache License, Version 2.0
Download-URL: https://github.com/dailymotion/cloudkey-py/zipball/1.2.6
Keywords: dailymotion,dmcloud,cloud,cloudkey,api,sdk
Platform: UNKNOWN
Classifier: Programming Language :: Python
Classifier: Development Status :: 5 - Production/Stable
Classifier: Intended Audience :: Developers
Classifier: License :: OSI Approved :: Apache Software License
Classifier: Operating System :: MacOS :: MacOS X
Classifier: Operating System :: Microsoft :: Windows
Classifier: Operating System :: POSIX
